vesselmatch/__init__.py
vesselmatch/exceptions.py
vesselmatch/vesselmatch.py
vesselmatch-0.1.0.dist-info/METADATA
vesselmatch-0.1.0.dist-info/WHEEL
vesselmatch-0.1.0.dist-info/top_level.txt
vesselmatch-0.1.0.dist-info/RECORD
