Metadata-Version: 2.4
Name: vesselmatch
Version: 0.1.0
Summary: Python client for vessel name-to-IMO enrichment service
Author: vesselmatch
Requires-Python: >=3.7
Requires-Dist: pandas>=1.5.0
Requires-Dist: requests
Requires-Dist: pyarrow
Dynamic: author
Dynamic: requires-dist
Dynamic: requires-python
Dynamic: summary
